ESSM/ESscoring.py
ESSM/__init__.py
ESSM/sampleData/ES_scoring/Mireuksan_sample.cpg
ESSM/sampleData/ES_scoring/Mireuksan_sample.dbf
ESSM/sampleData/ES_scoring/Mireuksan_sample.prj
ESSM/sampleData/ES_scoring/Mireuksan_sample.sbn
ESSM/sampleData/ES_scoring/Mireuksan_sample.sbx
ESSM/sampleData/ES_scoring/Mireuksan_sample.shp
ESSM/sampleData/ES_scoring/Mireuksan_sample.shp.xml
ESSM/sampleData/ES_scoring/Mireuksan_sample.shx
ESSMTools/ESscoring.py
ESSMTools/__init__.py
ESSMTools/sampleData/ES_scoring/Mireuksan_sample.cpg
ESSMTools/sampleData/ES_scoring/Mireuksan_sample.dbf
ESSMTools/sampleData/ES_scoring/Mireuksan_sample.prj
ESSMTools/sampleData/ES_scoring/Mireuksan_sample.sbn
ESSMTools/sampleData/ES_scoring/Mireuksan_sample.sbx
ESSMTools/sampleData/ES_scoring/Mireuksan_sample.shp
ESSMTools/sampleData/ES_scoring/Mireuksan_sample.shp.xml
ESSMTools/sampleData/ES_scoring/Mireuksan_sample.shx
ESSMTools-1.0.2.dist-info/METADATA
ESSMTools-1.0.2.dist-info/WHEEL
ESSMTools-1.0.2.dist-info/top_level.txt
ESSMTools-1.0.2.dist-info/RECORD
