Metadata-Version: 2.1
Name: ESSMTools
Version: 1.0.2
Summary: Ecosystem Service Scoring and Management tools
Home-page: https://github.com/MG-Choi/ESSM
Author: Moongi Choi, Jang-Hwan Jo
Author-email: mongil030233@gmail.com
License: UNKNOWN
Platform: UNKNOWN
Requires-Dist: tqdm
Requires-Dist: numpy
Requires-Dist: pandas
Requires-Dist: geopandas (>=0.14.0)
